LICENSE
Makefile
artificial_data_generator/__init__.py
artificial_data_generator/artificial_data_generator.py
artificial_data_generator/artificial_data_generator_tools.py
artificial_data_generator/visualizer.py
artificial_data_generator-0.0.3.dist-info/LICENSE
artificial_data_generator-0.0.3.dist-info/METADATA
artificial_data_generator-0.0.3.dist-info/WHEEL
artificial_data_generator-0.0.3.dist-info/RECORD
